timer.v
`timescale 1ns/1ns

module timer (
    input           clock,
    input           reset,
    output  reg     pulse
);

    reg [3:0]   count;
    wire        count_eq11;

    always @(posedge clock) begin
        if (reset | count_eq11) begin
            count <= 4'd0;
        end else begin
            count <= count + 1'b1;
        end
    end

    assign  count_eq11 = (count == 4'd11);

    always @(posedge clock) begin
        pulse <= count_eq11;
    end

endmodule


module tb_timer;

    reg     clock;
    reg     reset;
    wire    pulse;

    timer u_timer (
        .clock  (clock  ),
        .reset  (reset  ),
        .pulse  (pulse  )
    );

    initial begin
        forever begin
            clock = 0; #10;
            clock = 1; #10;
        end
    end

    initial begin
        reset = 0;
        repeat(5) @(posedge clock);
        reset <= 1;
        repeat(5) @(posedge clock);
        reset <= 0;
    end

    initial begin
        forever begin
            @(reset);
            $display("reset=%b at time %0d", reset, $time);
        end
    end

    initial begin
        forever begin
            @(pulse);
            $display("pulse=%b at time %0d", pulse, $time);
        end
    end

    initial begin
        #1000;
        $display("Simulation finished.");
        $finish;
    end

    initial begin
        $dumpfile("timer.vcd");
        $dumpvars(0, tb_timer);
    end

endmodule

timer.vcd
$date
    Wed Nov  8 01:32:07 2017
$end
$version
    GPLCVER_2.12a of 05/16/07
$end
$timescale
    1 ns
$end
$scope module tb_timer $end
$var reg       1 !    clock $end
$var wire       1 "    pulse $end
$var reg       1 #    reset $end
$scope module u_timer $end
$var wire       1 $    clock $end
$var reg       4 %    count [3:0] $end
$var wire       1 &    count_eq11 $end
$var reg       1 '    pulse $end
$var wire       1 (    reset $end
$upscope $end
$upscope $end
$enddefinitions $end
#0
$dumpvars
0$
bx %
x&
x'
0(
0!
x"
0#
$end
#10
1$
1!
#20
0$
0!
#30
1$
1!
#40
0$
0!
#50
1$
1!
#60
0$
0!
#70
1$
1!
#80
0$
0!
#90
1(
1#
1$
1!
#100
0$
0!
#110
0&
b0 %
1$
1!
#120
0$
0!
#130
0"
0'
1$
1!
#140
0$
0!
#150
1$
1!
#160
0$
0!
#170
1$
1!
#180
0$
0!
#190
0(
0#
1$
1!
#200
0$
0!
#210
b1 %
1$
1!
#220
0$
0!
#230
b10 %
1$
1!
#240
0$
0!
#250
b11 %
1$
1!
#260
0$
0!
#270
b100 %
1$
1!
#280
0$
0!
#290
b101 %
1$
1!
#300
0$
0!
#310
b110 %
1$
1!
#320
0$
0!
#330
b111 %
1$
1!
#340
0$
0!
#350
b1000 %
1$
1!
#360
0$
0!
#370
b1001 %
1$
1!
#380
0$
0!
#390
b1010 %
1$
1!
#400
0$
0!
#410
1&
b1011 %
1$
1!
#420
0$
0!
#430
1"
0&
1'
b0 %
1$
1!
#440
0$
0!
#450
0"
0'
b1 %
1$
1!
#460
0$
0!
#470
b10 %
1$
1!
#480
0$
0!
#490
b11 %
1$
1!
#500
0$
0!
#510
b100 %
1$
1!
#520
0$
0!
#530
b101 %
1$
1!
#540
0$
0!
#550
b110 %
1$
1!
#560
0$
0!
#570
b111 %
1$
1!
#580
0$
0!
#590
b1000 %
1$
1!
#600
0$
0!
#610
b1001 %
1$
1!
#620
0$
0!
#630
b1010 %
1$
1!
#640
0$
0!
#650
1&
b1011 %
1$
1!
#660
0$
0!
#670
1"
0&
1'
b0 %
1$
1!
#680
0$
0!
#690
0"
0'
b1 %
1$
1!
#700
0$
0!
#710
b10 %
1$
1!
#720
0$
0!
#730
b11 %
1$
1!
#740
0$
0!
#750
b100 %
1$
1!
#760
0$
0!
#770
b101 %
1$
1!
#780
0$
0!
#790
b110 %
1$
1!
#800
0$
0!
#810
b111 %
1$
1!
#820
0$
0!
#830
b1000 %
1$
1!
#840
0$
0!
#850
b1001 %
1$
1!
#860
0$
0!
#870
b1010 %
1$
1!
#880
0$
0!
#890
1&
b1011 %
1$
1!
#900
0$
0!
#910
1"
0&
1'
b0 %
1$
1!
#920
0$
0!
#930
0"
0'
b1 %
1$
1!
#940
0$
0!
#950
b10 %
1$
1!
#960
0$
0!
#970
b11 %
1$
1!
#980
0$
0!
#990
b100 %
1$
1!
